pysyn_data/__init__.py
pysyn_data-0.3.9.dist-info/METADATA
pysyn_data-0.3.9.dist-info/WHEEL
pysyn_data-0.3.9.dist-info/top_level.txt
pysyn_data-0.3.9.dist-info/RECORD
