Metadata-Version: 2.1
Name: pysyn-data
Version: 0.3.9
Summary: This package is for generating synthetic data using 4 models i.e Conditional Genrative Adveserial Networks(CTGAN), Gaussian Mixture Model (GMM), Prinicipal Component Analysis (PCA) and Bayesian Network (BN). It also informs the user which model will work best based on the input data characterisitics.
Author: Raghav-Ritesh-Tavlab
Author-email: raghav.20.rb@gmail.com
Classifier: Programming Language :: Python :: 3
Classifier: Operating System :: Unix
Classifier: Operating System :: MacOS :: MacOS X
Classifier: Operating System :: Microsoft :: Windows
